objectifiedrest/ORest.py
objectifiedrest/__init__.py
objectifiedrest-1.1.dist-info/METADATA
objectifiedrest-1.1.dist-info/WHEEL
objectifiedrest-1.1.dist-info/top_level.txt
objectifiedrest-1.1.dist-info/RECORD
