Metadata-Version: 2.1
Name: objectifiedrest
Version: 1.1
Summary: Wrapper for ORM style access to REST APIs
Home-page: UNKNOWN
Author: Shahnawaz Akhtar
Author-email: er.shahnawaz.akhtar@gmail.com
License: UNKNOWN
Keywords: python,rest,api,rest api,orm,rest orm,easy rest api access
Platform: UNKNOWN
